README.md
setup.cfg
setup.py
test/test-fs.py
test/test.py
upylib/__init__.py
upylib.egg-info/PKG-INFO
upylib.egg-info/SOURCES.txt
upylib.egg-info/dependency_links.txt
upylib.egg-info/not-zip-safe
upylib.egg-info/top_level.txt
upylib/db/__init__.py
upylib/db/dbfunc.py
upylib/db/test.py
upylib/db/test_db.py
upylib/db/umysql.py
upylib/db/usqlite.py
upylib/util/__init__.py
upylib/util/date.py
upylib/util/fs.py
upylib/util/image.py
upylib/util/net.py
upylib/util/regex.py
upylib/util/test.py
upylib/util/test_dinfo.py
upylib/util/test_ext.py
upylib/util/test_get_dir_list.py
upylib/util/test_get_file_list.py
upylib/util/test_image.py
upylib/util/test_net.py
upylib/util/tsvfile.py