Metadata-Version: 1.0
Name: upylib
Version: 0.4.23
Summary: UKi's small libraries
Home-page: https://gitlab.com
Author: windnc
Author-email: windnc@gmail.com
License: MIT
Platform: UNKNOWN
